pydantic_settings_logging/__init__.py
pydantic_settings_logging-0.1.1.dist-info/METADATA
pydantic_settings_logging-0.1.1.dist-info/WHEEL
pydantic_settings_logging-0.1.1.dist-info/licenses/LICENSE
pydantic_settings_logging-0.1.1.dist-info/RECORD
