Metadata-Version: 2.4
Name: pydantic-settings-logging
Version: 0.1.1
Summary: Pydantic models for Python logging configuration
Project-URL: Homepage, https://github.com/vduseev/pydantic-settings-logging
Project-URL: Repository, https://github.com/vduseev/pydantic-settings-logging
Project-URL: Issues, https://github.com/vduseev/pydantic-settings-logging/issues
Author-email: vduseev <vagiz@duseev.com>
License: Apache-2.0
License-File: LICENSE
Keywords: configuration,json,logging,pydantic,settings,toml
Classifier: Development Status :: 4 - Beta
Classifier: Intended Audience :: Developers
Classifier: License :: OSI Approved :: Apache Software License
Classifier: Programming Language :: Python :: 3
Classifier: Programming Language :: Python :: 3.10
Classifier: Programming Language :: Python :: 3.11
Classifier: Programming Language :: Python :: 3.12
Classifier: Programming Language :: Python :: 3.13
Classifier: Topic :: Software Development :: Libraries :: Python Modules
Classifier: Topic :: System :: Logging
Classifier: Typing :: Typed
Requires-Python: >=3.10
Requires-Dist: pydantic-settings>=2.0
Requires-Dist: pydantic>=2.0
Requires-Dist: tomli>=2.0; python_version < '3.11'
